empyscripts/__init__.py
empyscripts/fdesign.py
empyscripts/printinfo.py
empyscripts/tmtemod.py
empyscripts-0.3.2.dist-info/METADATA
empyscripts-0.3.2.dist-info/RECORD
empyscripts-0.3.2.dist-info/WHEEL
empyscripts-0.3.2.dist-info/top_level.txt
