Metadata-Version: 2.1
Name: empyscripts
Version: 0.3.2
Summary: Add-ons for empymod
Home-page: https://empymod.github.io
Author: Dieter Werthmüller
Author-email: dieter@werthmuller.org
License: Apache License V2.0
Download-URL: https://github.com/empymod/empyscripts/tarball/v0.3.2
Platform: UNKNOWN
Classifier: Development Status :: 5 - Production/Stable
Classifier: License :: OSI Approved :: Apache Software License
Classifier: Programming Language :: Python :: 3.4
Classifier: Programming Language :: Python :: 3.5
Classifier: Programming Language :: Python :: 3.6
Requires-Dist: numpy
Requires-Dist: scipy (!=0.19.0)
